polytts/__init__.py
polytts/audio.py
polytts/base.py
polytts/codecs.py
polytts/constants.py
polytts/validation.py
polytts/audio/default_en.mp3
polytts/audio/default_ja.mp3
polytts/audio/default_ko.mp3
polytts/audio/default_zh.mp3
polytts/providers/__init__.py
polytts/providers/elevenlabs.py
polytts/providers/fishaudio.py
polytts/providers/gptsovits.py
polytts/providers/kokoro.py
polytts/providers/openai.py
polytts-0.1.0.dist-info/licenses/LICENSE
polytts-0.1.0.dist-info/METADATA
polytts-0.1.0.dist-info/WHEEL
polytts-0.1.0.dist-info/top_level.txt
polytts-0.1.0.dist-info/RECORD
