Metadata-Version: 2.4
Name: polytts
Version: 0.1.0
Summary: A unified interface for multiple TTS providers requiring minimal code changes for hotswapping.
Project-URL: Homepage, https://github.com/spava002/PolyTTS.git
Keywords: tts,text-to-speech,speech-synthesis,audio,voice
Classifier: Development Status :: 3 - Alpha
Classifier: Intended Audience :: Developers
Classifier: License :: OSI Approved :: MIT License
Classifier: Programming Language :: Python :: 3
Classifier: Programming Language :: Python :: 3.9
Classifier: Programming Language :: Python :: 3.10
Classifier: Programming Language :: Python :: 3.11
Classifier: Programming Language :: Python :: 3.12
Classifier: Programming Language :: Python :: 3.13
Requires-Python: >=3.9
License-File: LICENSE
Requires-Dist: numpy<2.0
Requires-Dist: python-dotenv
Provides-Extra: dev
Requires-Dist: pytest; extra == "dev"
Requires-Dist: filetype; extra == "dev"
Requires-Dist: mutagen; extra == "dev"
Requires-Dist: pydub; extra == "dev"
Provides-Extra: openai
Requires-Dist: openai; extra == "openai"
Provides-Extra: elevenlabs
Requires-Dist: elevenlabs; extra == "elevenlabs"
Provides-Extra: fishaudio
Requires-Dist: fish-audio-sdk; extra == "fishaudio"
Provides-Extra: kokoro
Requires-Dist: kokoro; extra == "kokoro"
Provides-Extra: all
Requires-Dist: openai; extra == "all"
Requires-Dist: elevenlabs; extra == "all"
Requires-Dist: fish-audio-sdk; extra == "all"
Requires-Dist: kokoro; extra == "all"
Dynamic: license-file
